mplsports/__init__.py
mplsports/utils.py
mplsports/dimensions/basketball/standard.yaml
mplsports/dimensions/handball/standard.yaml
mplsports/dimensions/soccer/standard.yaml
mplsports/dimensions/tennis/standard.yaml
mplsports/dimensions/volleyball/standard.yaml
mplsports/geometry/__init__.py
mplsports/geometry/arc.py
mplsports/geometry/circle.py
mplsports/geometry/line.py
mplsports/pitch/__init__.py
mplsports/pitch/base.py
mplsports/pitch/basketball.py
mplsports/pitch/handball.py
mplsports/pitch/soccer.py
mplsports/pitch/tennis.py
mplsports/pitch/volleyball.py
mplsports-0.2.2.dist-info/METADATA
mplsports-0.2.2.dist-info/WHEEL
mplsports-0.2.2.dist-info/top_level.txt
mplsports-0.2.2.dist-info/RECORD
