Metadata-Version: 2.1
Name: mplsports
Version: 0.2.2
Summary: A library to plot various sports fields using Matplotlib
Requires-Python: >=3.8
Requires-Dist: matplotlib>=3.7.5
